{"title": "[\ub179] \uc5f0\uc911 \uc81c16\uc8fc\uac04 \ud654\uc694\uc77c \ub610\ub294 [\ubc31] \uc131\ub140 \ube44\ub974\uc9c0\ud0c0 \uc218\ub3c4\uc790", "date": "2024\ub144 07\uc6d4 23\uc77c \ud654\uc694\uc77c", "explanation": "", "sections": [{"title": "\uc785\ub2f9\uc1a1", "source": "\uc2dc\ud3b8 54(53),6.8", "content": {"data": "\ubcf4\ub77c, \ud558\ub290\ub2d8\uc740 \ub098\ub97c \ub3c4\uc6b0\uc2dc\ub294 \ubd84, \uc8fc\ub2d8\uc740 \ub0b4 \uc0dd\uba85\uc744 \ub5a0\ubc1b\uce58\ub294 \ubd84\uc774\uc2dc\ub2e4. \uc800\ub294 \uae30\uaebc\uc774 \ub2f9\uc2e0\uaed8 \uc81c\ubb3c\uc744 \ubc14\uce58\ub9ac\uc774\ub2e4. \uc8fc\ub2d8, \uc88b\uc73c\uc2e0 \ub2f9\uc2e0 \uc774\ub984 \ucc2c\uc1a1\ud558\ub9ac\uc774\ub2e4.\n"}}, {"title": "\ubcf8\uae30\ub3c4", "content": {"data": "\uc8fc\ub2d8, \uc8fc\ub2d8\uc758 \uc885\ub4e4\uc5d0\uac8c \uc790\ube44\ub97c \ubca0\ud478\uc2dc\uace0 \uc8fc\ub2d8\uc758 \uc740\ucd1d\uc744 \uc778\uc790\ub85c\uc774 \ub354\ud574 \uc8fc\uc2dc\uc5b4\n\ubbff\uc74c\uacfc \ud76c\ub9dd\uacfc \uc0ac\ub791\uc73c\ub85c\n\uc5b8\uc81c\ub098 \uae68\uc5b4 \uc8fc\ub2d8\uc758 \uacc4\uba85\uc744 \ucda9\uc2e4\ud788 \uc9c0\ud0a4\uac8c \ud558\uc18c\uc11c.\n\uc131\ubd80\uc640 \uc131\ub839\uacfc \u2026\u2026.\n"}}, {"title": "\uc81c1\ub3c5\uc11c", "sub_title": "<\uc800\ud76c\uc758 \ubaa8\ub4e0 \uc8c4\uc545\uc744 \ubc14\ub2e4 \uae4a\uc740 \uacf3\uc73c\ub85c \ub358\uc838 \uc8fc\uc2ed\uc2dc\uc624.>", "content": {"source": {"index": "7,14-15.18-20", "book": "\u25a5 \ubbf8\uce74 \uc608\uc5b8\uc11c\uc758 \ub9d0\uc500\uc785\ub2c8\ub2e4."}, "data": "\uc8fc\ub2d8, 14 \uacfc\uc218\uc6d0 \ud55c\uac00\uc6b4\ub370 \uc232\uc18d\uc5d0 \ud640\ub85c \uc0b4\uc544\uac00\ub294 \ub2f9\uc2e0 \ubc31\uc131\uc744,\n\ub2f9\uc2e0 \uc18c\uc720\uc758 \uc591 \ub5bc\ub97c \ub2f9\uc2e0\uc758 \uc9c0\ud321\uc774\ub85c \ubcf4\uc0b4\ud3b4 \uc8fc\uc2ed\uc2dc\uc624.\n\uc61b\ub0a0\ucc98\ub7fc \ubc14\uc0b0\uacfc \uae38\uc557\uc5d0\uc11c \uadf8\ub4e4\uc744 \ubcf4\uc0b4\ud3b4 \uc8fc\uc2ed\uc2dc\uc624.\n15 \ub2f9\uc2e0\uaed8\uc11c \uc774\uc9d1\ud2b8 \ub545\uc5d0\uc11c \ub098\uc624\uc2e4 \ub54c\ucc98\ub7fc\n\uc800\ud76c\uc5d0\uac8c \ub180\ub77c\uc6b4 \uc77c\ub4e4\uc744 \ubcf4\uc5ec \uc8fc\uc2ed\uc2dc\uc624.\n18 \ub2f9\uc2e0\uc758 \uc18c\uc720\uc778 \ub0a8\uc740 \uc790\ub4e4, \uadf8\ub4e4\uc758 \ud5c8\ubb3c\uc744 \uc6a9\uc11c\ud574 \uc8fc\uc2dc\uace0\n\uc8c4\ub97c \ubabb \ubcf8 \uccb4\ud574 \uc8fc\uc2dc\ub294 \ub2f9\uc2e0 \uac19\uc73c\uc2e0 \ud558\ub290\ub2d8\uc774 \uc5b4\ub514 \uc788\uaca0\uc2b5\ub2c8\uae4c?\n\uadf8\ubd84\uc740 \ubd84\ub178\ub97c \uc601\uc6d0\ud788 \ud488\uc9c0 \uc54a\uc73c\uc2dc\uace0\n\uc624\ud788\ub824 \uae30\uaebc\uc774 \uc790\uc560\ub97c \ubca0\ud478\uc2dc\ub294 \ubd84\uc774\uc2dc\ub2e4.\n19 \uadf8\ubd84\uaed8\uc11c\ub294 \ub2e4\uc2dc \uc6b0\ub9ac\ub97c \uac00\uc5fe\uc774 \uc5ec\uae30\uc2dc\uace0\n\uc6b0\ub9ac\uc758 \ud5c8\ubb3c\ub4e4\uc744 \ubaa8\ub974\ub294 \uccb4\ud574 \uc8fc\uc2dc\ub9ac\ub77c.\n\ub2f9\uc2e0\uaed8\uc11c \uc800\ud76c\uc758 \ubaa8\ub4e0 \uc8c4\uc545\uc744 \ubc14\ub2e4 \uae4a\uc740 \uacf3\uc73c\ub85c \ub358\uc838 \uc8fc\uc2ed\uc2dc\uc624.\n20 \uba3c \uc61b\ub0a0 \ub2f9\uc2e0\uaed8\uc11c \uc800\ud76c \uc870\uc0c1\ub4e4\uc5d0\uac8c \ub9f9\uc138\ud558\uc2e0 \ub300\ub85c\n\uc57c\uacf1\uc744 \uc131\uc2e4\ud788 \ub300\ud558\uc2dc\uace0 \uc544\ube0c\ub77c\ud568\uc5d0\uac8c \uc790\uc560\ub97c \ubca0\ud480\uc5b4 \uc8fc\uc2ed\uc2dc\uc624.\n\uc8fc\ub2d8\uc758 \ub9d0\uc500\uc785\ub2c8\ub2e4.\n\u25ce \ud558\ub290\ub2d8, \uac10\uc0ac\ud569\ub2c8\ub2e4.\n"}}, {"title": "\ud654\ub2f5\uc1a1", "source": "\uc2dc\ud3b8\u00a085(84),2-4.5-6.7-8(\u25ce 8\u3131)", "content": {"data": "\u25ce \uc8fc\ub2d8, \uc800\ud76c\uc5d0\uac8c \ub2f9\uc2e0 \uc790\uc560\ub97c \ubcf4\uc5ec \uc8fc\uc18c\uc11c.\n\u25cb \uc8fc\ub2d8, \ub2f9\uc2e0 \ub545\uc744 \uc5b4\uc5ec\uc090 \uc5ec\uae30\uc2dc\uc5b4, \uc57c\uacf1\uc758 \uadc0\uc591\uc744 \ud480\uc5b4 \uc8fc\uc168\ub098\uc774\ub2e4. \ub2f9\uc2e0 \ubc31\uc131\uc758 \uc8c4\ub97c \uc6a9\uc11c\ud558\uc2dc\uace0, \ubaa8\ub4e0 \uc798\ubabb\uc744 \ub36e\uc5b4 \uc8fc\uc168\ub098\uc774\ub2e4. \ub2f9\uc2e0\uc758 \uaca9\ubd84\uc744 \ub9d0\ub054\ud788 \uc53b\uc73c\uc2dc\uace0, \ubd84\ub178\uc758 \uc5f4\uae30\ub97c \uac70\ub450\uc168\ub098\uc774\ub2e4. \u25ce\n\u25cb \uc800\ud76c \uad6c\uc6d0\uc758 \ud558\ub290\ub2d8, \uc800\ud76c\ub97c \ub2e4\uc2dc \uc77c\uc73c\ud0a4\uc18c\uc11c. \uc800\ud76c\uc5d0\uac8c \ud488\uc740 \ub178\uc5ec\uc6c0\uc744 \ud480\uc5b4 \uc8fc\uc18c\uc11c. \ub05d\ub05d\ub0b4 \uc800\ud76c\uc5d0\uac8c \uc9c4\ub178\ud558\uc2dc\ub835\ub2c8\uae4c? \ub300\ub300\ub85c \ub2f9\uc2e0 \ubd84\ub178\ub97c \ubed7\uce58\uc2dc\ub835\ub2c8\uae4c? \u25ce\n\u25cb \uc800\ud76c\uc5d0\uac8c \uc0dd\uba85\uc744 \ub3cc\ub824\uc8fc\uc2dc\uc5b4, \ub2f9\uc2e0 \ubc31\uc131\uc774 \ub2f9\uc2e0 \uc548\uc5d0\uc11c \uae30\ubed0\ud558\uac8c \ud558\uc18c\uc11c. \uc8fc\ub2d8, \uc800\ud76c\uc5d0\uac8c \ub2f9\uc2e0 \uc790\uc560\ub97c \ubcf4\uc5ec \uc8fc\uc2dc\uace0, \ub2f9\uc2e0 \uad6c\uc6d0\uc744 \ubca0\ud480\uc5b4 \uc8fc\uc18c\uc11c. \u25ce\n"}}, {"title": "\ubcf5\uc74c \ud658\ud638\uc1a1", "source": "\uc694\ud55c\u00a014,23 \ucc38\uc870", "content": {"data": "\u25ce \uc54c\ub810\ub8e8\uc57c.\n\u25cb \uc8fc\ub2d8\uc774 \ub9d0\uc500\ud558\uc2e0\ub2e4. \ub204\uad6c\ub4e0\uc9c0 \ub098\ub97c \uc0ac\ub791\ud558\uba74 \ub0b4 \ub9d0\uc744 \uc9c0\ud0a4\ub9ac\ub2c8 \ub0b4 \uc544\ubc84\uc9c0\ub3c4 \uadf8\ub97c \uc0ac\ub791\ud558\uc2dc\uace0 \uc6b0\ub9ac\uac00 \uac00\uc11c \uadf8\uc640 \ud568\uaed8 \uc0b4\ub9ac\ub77c.\n\u25ce \uc54c\ub810\ub8e8\uc57c.\n"}}, {"title": "\ubcf5\uc74c", "sub_title": "<\uc608\uc218\ub2d8\uaed8\uc11c \uc81c\uc790\ub4e4\uc744 \uac00\ub9ac\ud0a4\uc2dc\uba70 \uc774\ub974\uc168\ub2e4. \u201c\uc774\ub4e4\uc774 \ub0b4 \uc5b4\uba38\ub2c8\uace0 \ub0b4 \ud615\uc81c\ub4e4\uc774\ub2e4.\u201d>", "content": {"source": {"index": "12,46-50", "book": "\u2720 \ub9c8\ud0dc\uc624\uac00 \uc804\ud55c \uac70\ub8e9\ud55c \ubcf5\uc74c\uc785\ub2c8\ub2e4."}, "data": "\uadf8\ub54c\uc5d0 46 \uc608\uc218\ub2d8\uaed8\uc11c \uad70\uc911\uc5d0\uac8c \ub9d0\uc500\ud558\uace0 \uacc4\uc2dc\ub294\ub370,\n\uadf8\ubd84\uc758 \uc5b4\uba38\ub2c8\uc640 \ud615\uc81c\ub4e4\uc774 \uadf8\ubd84\uacfc \uc774\uc57c\uae30\ud558\ub824\uace0 \ubc16\uc5d0 \uc11c \uc788\uc5c8\ub2e4.\n47 \uadf8\ub798\uc11c \uc5b4\ub5a4 \uc774\uac00 \uc608\uc218\ub2d8\uaed8,\n\u201c\ubcf4\uc2ed\uc2dc\uc624, \uc2a4\uc2b9\ub2d8\uc758 \uc5b4\uba38\ub2d8\uacfc \ud615\uc81c\ub4e4\uc774\n\uc2a4\uc2b9\ub2d8\uacfc \uc774\uc57c\uae30\ud558\ub824\uace0 \ubc16\uc5d0 \uc11c \uacc4\uc2ed\ub2c8\ub2e4.\u201d \ud558\uace0 \ub9d0\ud558\uc600\ub2e4.\n48 \uadf8\ub7ec\uc790 \uc608\uc218\ub2d8\uaed8\uc11c \ub2f9\uc2e0\uaed8 \ub9d0\ud55c \uc0ac\ub78c\uc5d0\uac8c,\n\u201c\ub204\uac00 \ub0b4 \uc5b4\uba38\ub2c8\uace0 \ub204\uac00 \ub0b4 \ud615\uc81c\ub4e4\uc774\ub0d0?\u201d \ud558\uace0 \ubc18\ubb38\ud558\uc168\ub2e4.\n49 \uadf8\ub9ac\uace0 \ub2f9\uc2e0\uc758 \uc81c\uc790\ub4e4\uc744 \uac00\ub9ac\ud0a4\uc2dc\uba70 \uc774\ub974\uc168\ub2e4.\n\u201c\uc774\ub4e4\uc774 \ub0b4 \uc5b4\uba38\ub2c8\uace0 \ub0b4 \ud615\uc81c\ub4e4\uc774\ub2e4.\n50 \ud558\ub298\uc5d0 \uacc4\uc2e0 \ub0b4 \uc544\ubc84\uc9c0\uc758 \ub73b\uc744 \uc2e4\ud589\ud558\ub294 \uc0ac\ub78c\uc774\n\ub0b4 \ud615\uc81c\uc694 \ub204\uc774\uc694 \uc5b4\uba38\ub2c8\ub2e4.\u201d\n\uc8fc\ub2d8\uc758 \ub9d0\uc500\uc785\ub2c8\ub2e4.\n\u25ce \uadf8\ub9ac\uc2a4\ub3c4\ub2d8, \ucc2c\ubbf8\ud569\ub2c8\ub2e4.\n"}}, {"title": "\uc608\ubb3c \uae30\ub3c4", "content": {"data": "\ud558\ub290\ub2d8, \uad6c\uc57d\uc758 \uc81c\uc0ac\ub4e4\uc744 \ud558\ub098\uc758 \uc81c\uc0ac\ub85c \uc644\uc131\ud558\uc168\uc73c\ub2c8\n\ud558\ub290\ub2d8\uc758 \uc885\ub4e4\uc774 \uc815\uc131\uaecf \ubc14\uce58\ub294 \uc774 \uc608\ubb3c\uc744 \ubc1b\uc73c\uc2dc\uace0\n\uc544\ubca8\uc758 \uc81c\ubb3c\ucc98\ub7fc \uac15\ubcf5\ud558\uc2dc\uace0 \uac70\ub8e9\ud558\uac8c \ud558\uc2dc\uc5b4\n\uc874\uc5c4\ud558\uc2e0 \ud558\ub290\ub2d8\uc758 \uc601\uad11\uc744 \uc704\ud558\uc5ec \ubd09\ud5cc\ud558\ub294 \uc774 \uc81c\uc0ac\uac00\n\uc778\ub958 \uad6c\uc6d0\uc5d0 \ub3c4\uc6c0\uc774 \ub418\uac8c \ud558\uc18c\uc11c.\n\uc6b0\ub9ac \uc8fc \u2026\u2026.\n"}}, {"title": "\uc601\uc131\uccb4\uc1a1", "source": "\uc2dc\ud3b8 111(110),4-5", "content": {"data": "\ub2f9\uc2e0 \uae30\uc801\ub4e4 \uae30\uc5b5\ud558\uac8c \ud558\uc2dc\ub2c8, \uc8fc\ub2d8\uc740 \ub108\uadf8\ub7fd\uace0 \uc790\ube44\ub85c\uc6b0\uc2dc\ub2e4. \ub2f9\uc2e0 \uacbd\uc678\ud558\ub294 \uc774\ub4e4\uc5d0\uac8c \uc591\uc2dd\uc744 \uc8fc\uc2e0\ub2e4.\n", "alternative": "<\ub610\ub294>\n\n\ubb35\uc2dc 3,20 \ucc38\uc870\n\n\uc8fc\ub2d8\uc774 \ub9d0\uc500\ud558\uc2e0\ub2e4. \ubcf4\ub77c, \ub0b4\uac00 \ubb38 \uc55e\uc5d0 \uc11c\uc11c \ubb38\uc744 \ub450\ub4dc\ub9ac\uace0 \uc788\ub2e4. \ub204\uad6c\ub4e0\uc9c0 \ub0b4 \ubaa9\uc18c\ub9ac\ub97c \ub4e3\uace0 \ubb38\uc744 \uc5f4\uba74, \ub098\ub294 \uadf8\uc758 \uc9d1\uc5d0 \ub4e4\uc5b4\uac00 \uadf8\uc640 \ud568\uaed8 \uba39\uace0, \uadf8 \uc0ac\ub78c\ub3c4 \ub098\uc640 \ud568\uaed8 \uba39\uc73c\ub9ac\ub77c."}}, {"title": "\uc601\uc131\uccb4 \ud6c4 \ubb35\uc0c1", "content": {"data": "<\uadf8\ub9ac\uc2a4\ub3c4\uc640 \uc77c\uce58\ub97c \uc774\ub8e8\ub294 \uac00\uc6b4\ub370 \uc7a0\uc2dc \ub9c8\uc74c\uc18d\uc73c\ub85c \uae30\ub3c4\ud569\uc2dc\ub2e4.>"}}, {"title": "\uc601\uc131\uccb4 \ud6c4 \uae30\ub3c4", "content": {"data": "\uc8fc\ub2d8, \uc774 \uac70\ub8e9\ud55c \uc2e0\ube44\uc758 \uc740\ucd1d\uc73c\ub85c \uc800\ud76c\ub97c \uac00\ub4dd \ucc44\uc6cc \uc8fc\uc168\uc73c\ub2c8\n\uc790\ube44\ub85c\uc774 \ub3c4\uc640\uc8fc\uc2dc\uc5b4\n\uc800\ud76c\uac00 \uc61b \uc0b6\uc744 \ubc84\ub9ac\uace0 \uc0c8 \uc0b6\uc744 \uc0b4\uc544\uac00\uac8c \ud558\uc18c\uc11c.\n\uc6b0\ub9ac \uc8fc \u2026\u2026.\n"}}]}